owl2conv/__init__.py
owl2conv/owlobjects.py
owl2else-0.9.5.data/scripts/owl2clips
owl2else-0.9.5.data/scripts/owl2clips.bat
owl2else-0.9.5.data/scripts/owl2plot
owl2else-0.9.5.data/scripts/owl2plot.bat
owl2else-0.9.5.data/scripts/owl2rdflib
owl2else-0.9.5.data/scripts/owl2rdflib.bat
owl2else-0.9.5.dist-info/LICENSE
owl2else-0.9.5.dist-info/METADATA
owl2else-0.9.5.dist-info/WHEEL
owl2else-0.9.5.dist-info/top_level.txt
owl2else-0.9.5.dist-info/RECORD
