Metadata-Version: 2.1
Name: owl2else
Version: 0.9.5
Summary: Utilities to transform ontology OWL2 files to other formats
Home-page: https://github.com/bejar/owl2else
Author: Javier Bejar
Author-email: bejar@cs.upc.edu
Classifier: Programming Language :: Python :: 3
Classifier: License :: OSI Approved :: MIT License
Classifier: Operating System :: OS Independent
Requires-Python: >=3.7
License-File: LICENSE
Requires-Dist: rdflib
Requires-Dist: matplotlib
Requires-Dist: graphviz
